lynxy/__init__.py
lynxy/comm.py
lynxy/constants.py
lynxy/exceptions.py
lynxy/lynx.py
lynxy/parser.py
lynxy/pool.py
lynxy/sec.py
lynxy-1.0.0.dist-info/METADATA
lynxy-1.0.0.dist-info/WHEEL
lynxy-1.0.0.dist-info/licenses/LICENSE
lynxy-1.0.0.dist-info/RECORD
